infinitydb/__init__.py
infinitydb/access.py
infinitydb-1.0.6.dist-info/METADATA
infinitydb-1.0.6.dist-info/WHEEL
infinitydb-1.0.6.dist-info/licenses/LICENSE
infinitydb-1.0.6.dist-info/RECORD
