Metadata-Version: 2.3
Name: infinitydb
Version: 1.0.6
Summary: Access to the InfinityDB server via REST
Project-URL: Homepage, https://boilerbay.com
Author-email: Roger Deran <roger.deran@gmail.com>
License-File: LICENSE
Classifier: License :: OSI Approved :: MIT License
Classifier: Operating System :: OS Independent
Classifier: Programming Language :: Python :: 3
Requires-Python: >=3.0
Requires-Dist: python-dateutil>=2.8.2
Requires-Dist: requests
